pmag_tilt/__init__.py
pmag_tilt/pmag_tilt.py
pmag_tilt-1.0.0.dist-info/METADATA
pmag_tilt-1.0.0.dist-info/WHEEL
pmag_tilt-1.0.0.dist-info/licenses/LICENSE
pmag_tilt-1.0.0.dist-info/RECORD
